pydwg/__init__.py
pydwg/_version.py
pydwg/cli.py
pydwg/config.py
pydwg/dbm.py
pydwg/generator.py
pydwg/myAutoCAD.py
pydwg-1.0.0.dist-info/licenses/LICENSE
tests/__init__.py
tests/test_generator.py
pydwg-1.0.0.dist-info/METADATA
pydwg-1.0.0.dist-info/WHEEL
pydwg-1.0.0.dist-info/entry_points.txt
pydwg-1.0.0.dist-info/top_level.txt
pydwg-1.0.0.dist-info/RECORD
