Metadata-Version: 2.4
Name: pydwg
Version: 1.0.0
Summary: A Python package for generating drilling patterns for tunnel excavation based on AutoCAD polylines
Home-page: https://github.com/SanjeevBashyal/UTHP
Author: Sanjeev Bashyal
Author-email: Sanjeev Bashyal <sanjeev.bashyal01@gmail.com>
Maintainer-email: Sanjeev Bashyal <sanjeev.bashyal01@gmail.com>
License: MIT
Project-URL: Homepage, https://github.com/SanjeevBashyal/UTHP
Project-URL: Documentation, https://github.com/SanjeevBashyal/UTHP
Project-URL: Repository, https://github.com/SanjeevBashyal/UTHP
Project-URL: Bug Tracker, https://github.com/SanjeevBashyal/UTHP/issues
Keywords: drilling,pattern,tunnel,excavation,autocad,civil engineering,mining
Classifier: Development Status :: 4 - Beta
Classifier: Intended Audience :: Science/Research
Classifier: Intended Audience :: Developers
Classifier: License :: OSI Approved :: MIT License
Classifier: Operating System :: OS Independent
Classifier: Programming Language :: Python :: 3
Classifier: Programming Language :: Python :: 3.7
Classifier: Programming Language :: Python :: 3.8
Classifier: Programming Language :: Python :: 3.9
Classifier: Programming Language :: Python :: 3.10
Classifier: Programming Language :: Python :: 3.11
Classifier: Programming Language :: Python :: 3.12
Classifier: Topic :: Scientific/Engineering
Classifier: Topic :: Software Development :: Libraries :: Python Modules
Requires-Python: >=3.7
License-File: LICENSE
Requires-Dist: pyautocad>=0.2.0
Requires-Dist: numpy>=1.19.0
Provides-Extra: dev
Requires-Dist: pytest>=6.0; extra == "dev"
Requires-Dist: pytest-cov>=2.0; extra == "dev"
Requires-Dist: black>=21.0; extra == "dev"
Requires-Dist: flake8>=3.8; extra == "dev"
Requires-Dist: mypy>=0.800; extra == "dev"
Dynamic: author
Dynamic: home-page
Dynamic: license-file
Dynamic: requires-python
